dashboard_compiler/__init__.py
dashboard_compiler/cli.py
dashboard_compiler/cli_context.py
dashboard_compiler/cli_local.py
dashboard_compiler/cli_options.py
dashboard_compiler/cli_output.py
dashboard_compiler/cli_remote.py
dashboard_compiler/lsp/__init__.py
dashboard_compiler/lsp/grid_extractor.py
dashboard_compiler/lsp/grid_updater.py
dashboard_compiler/lsp/models.py
dashboard_compiler/lsp/server.py
dashboard_compiler/lsp/utils.py
dashboard_compiler/sample_data/__init__.py
dashboard_compiler/sample_data/loader.py
dashboard_compiler/tools/__init__.py
kb_dashboard_cli-0.2.7.dist-info/WHEEL
kb_dashboard_cli-0.2.7.dist-info/entry_points.txt
kb_dashboard_cli-0.2.7.dist-info/METADATA
kb_dashboard_cli-0.2.7.dist-info/RECORD
