Metadata-Version: 2.3
Name: kb-dashboard-cli
Version: 0.2.7
Summary: CLI, LSP, and future MCP server for kb-yaml-to-lens dashboard compiler
License: MIT
Classifier: Development Status :: 3 - Alpha
Classifier: Intended Audience :: Developers
Classifier: License :: OSI Approved :: MIT License
Classifier: Programming Language :: Python :: 3
Classifier: Programming Language :: Python :: 3.12
Classifier: Topic :: Software Development :: Code Generators
Requires-Dist: kb-dashboard-core==0.2.7
Requires-Dist: kb-dashboard-tools==0.2.7
Requires-Dist: click>=8.3
Requires-Dist: rich-click>=1.9.0
Requires-Dist: elasticsearch>=8.16.2
Requires-Dist: pygls>=2.0.0
Requires-Dist: lsprotocol>=2024.0.0
Requires-Python: >=3.12
